lazyt/__init__.py
lazyt/__main__.py
lazyt/example.py
lazyt/lazyt.py
lazyt-1.1.1.dist-info/METADATA
lazyt-1.1.1.dist-info/WHEEL
lazyt-1.1.1.dist-info/top_level.txt
lazyt-1.1.1.dist-info/RECORD
