Metadata-Version: 2.1
Name: lazyt
Version: 1.1.1
Summary: Usefull methods cause i'm lazy and they made everything easier and fancier(check project link for a decent README)
Home-page: https://gitlab.com/ThomasAndreatta/lazyt
Author: Andreatta
License: MIT
Platform: UNKNOWN
Classifier: License :: OSI Approved :: MIT License
Classifier: Programming Language :: Python :: 3
Classifier: Programming Language :: Python :: 3.7
Classifier: Programming Language :: Python :: 3.8
Classifier: Programming Language :: Python :: 3.10
Requires-Dist: sty
